ms_ipv6/__init__.py
ms_ipv6/cli.py
ms_ipv6/downloader.py
ms_ipv6/schema.py
ms_ipv6/utils.py
ms_ipv6-0.1.1.dist-info/licenses/LICENSE
ms_ipv6-0.1.1.dist-info/METADATA
ms_ipv6-0.1.1.dist-info/WHEEL
ms_ipv6-0.1.1.dist-info/entry_points.txt
ms_ipv6-0.1.1.dist-info/top_level.txt
ms_ipv6-0.1.1.dist-info/RECORD
