Metadata-Version: 2.4
Name: ms-ipv6
Version: 0.1.1
Summary: A Python package to assist with ModelScope downloads
Author-email: Yanyi Liu <wolfsonliu@163.com>
License: MIT
Project-URL: Homepage, https://github.com/liuyanyi/ms_ipv6
Project-URL: Repository, https://github.com/liuyanyi/ms_ipv6
Project-URL: Issues, https://github.com/liuyanyi/ms_ipv6/issues
Classifier: Development Status :: 3 - Alpha
Classifier: Intended Audience :: Developers
Classifier: License :: OSI Approved :: MIT License
Classifier: Operating System :: OS Independent
Classifier: Programming Language :: Python :: 3
Classifier: Programming Language :: Python :: 3.8
Classifier: Programming Language :: Python :: 3.9
Classifier: Programming Language :: Python :: 3.10
Classifier: Programming Language :: Python :: 3.11
Requires-Python: >=3.8
License-File: LICENSE
Requires-Dist: httpx>=0.27.0
Requires-Dist: click>=8.0.0
Requires-Dist: tqdm>=4.66.0
Requires-Dist: loguru>=0.7.0
Provides-Extra: dev
Requires-Dist: pytest>=6.0.0; extra == "dev"
Requires-Dist: ruff>=0.1.0; extra == "dev"
Requires-Dist: mypy>=0.900; extra == "dev"
Requires-Dist: build>=0.10.0; extra == "dev"
Requires-Dist: twine>=4.0.0; extra == "dev"
Provides-Extra: plan
Requires-Dist: modelscope>=1.16.0; extra == "plan"
Dynamic: license-file
